chessencryption/__init__.py
chessencryption/decode.py
chessencryption/encode.py
chessencryption/util.py
chessencryption-1.1.dist-info/METADATA
chessencryption-1.1.dist-info/WHEEL
chessencryption-1.1.dist-info/top_level.txt
chessencryption-1.1.dist-info/RECORD
