Metadata-Version: 2.1
Name: chessencryption
Version: 1.1
Requires-Dist: chess
Requires-Dist: flask
